{
  "development": {
    "username": "root",
    "password": "root123",
    "database": "aiva_dev",
    "host": "127.0.0.1",
    "dialect": "mysql",
    "logging": false
  },
  "test": {
    "username": "root",
    "password": "root123",
    "database": "aiva_test",
    "host": "127.0.0.1",
    "dialect": "mysql",
    "logging": false
  },
  "production": {
    "username": "root",
    "password": "root123",
    "database": "aiva_prod",
    "host": "127.0.0.1",
    "dialect": "mysql",
    "logging": false
  }
}
